Stock_package/Stocks.py
Stock_package/__init__.py
StockDSNE-0.0.1.dist-info/METADATA
StockDSNE-0.0.1.dist-info/WHEEL
StockDSNE-0.0.1.dist-info/top_level.txt
StockDSNE-0.0.1.dist-info/RECORD
