Metadata-Version: 2.1
Name: StockDSNE
Version: 0.0.1
Summary: Stock assist
Author: David
Author-email: <daviddadiomov@gmail.com>
License: UNKNOWN
Keywords: stock
Platform: UNKNOWN
Classifier: Development Status :: 1 - Planning
Classifier: Intended Audience :: Developers
Classifier: Programming Language :: Python :: 3
Classifier: Operating System :: Unix
Classifier: Operating System :: MacOS :: MacOS X
Classifier: Operating System :: Microsoft :: Windows
Requires-Dist: bs4
Requires-Dist: requests
Requires-Dist: Datetime
Requires-Dist: pandas
Requires-Dist: matplotlib
Requires-Dist: termcolor
Requires-Dist: lxml
